webkitapipy_additions/program.pyi
webkitapipy_additions-0.1.0.dist-info/METADATA
webkitapipy_additions-0.1.0.dist-info/WHEEL
webkitapipy_additions-0.1.0.dist-info/top_level.txt
webkitapipy_additions-0.1.0.dist-info/RECORD
